[{"firstname":"Omar","miidlename":"Ihab","lastname":"Shehata","emailaddress":"someemail@email.com","password":"Egypt","city":"Cairo","streetaddress":"123street","postalcode":"123abc"},{"firstname":"Omar","miidlename":"Ihab","lastname":"Shehata","emailaddress":"someemail@email.com","password":"Egypt","city":"Cairo","streetaddress":"123street","postalcode":"123abc"},{"firstname":"Omar","middlename":"something","lastname":"Shehata","emailaddress":"omarihab.uniapp@gmail.com","password":"whatever","city":"Montr\u00e9al","streetaddress":"1234","postalcode":"H3G 2A4"}]